spc/__init__.py
spc/bot.py
spc/const.py
spc/database.py
spc/objects.py
sulvion_picord-0.1.4.dist-info/licenses/LICENSE
sulvion_picord-0.1.4.dist-info/METADATA
sulvion_picord-0.1.4.dist-info/WHEEL
sulvion_picord-0.1.4.dist-info/top_level.txt
sulvion_picord-0.1.4.dist-info/RECORD
