Metadata-Version: 2.4
Name: sulvion-picord
Version: 0.1.4
Summary: Discord bot wrapper dengan syntax sederhana dan powerful
Home-page: https://github.com/HafizDaffa01/SulvionPiCord
Author: Sulfuric
Author-email: hafizdaffaw+dev@gmail.com
License: MIT
Classifier: Programming Language :: Python :: 3
Classifier: License :: OSI Approved :: MIT License
Classifier: Operating System :: OS Independent
Requires-Python: >=3.8
License-File: LICENSE
Requires-Dist: discord.py>=2.5.2
Requires-Dist: typing-extensions>=4.5.0
Dynamic: license-file
